[
        {
            "x": -177.191,
            "y": -168.260,
            "z": 39.000,
            "t":1.2
        },
        {
            "x": -168.659,
            "y": -163.359,
            "z": 39.000,
            "t":1.6
        },
        {
            "x": -164.890,
            "y": -151.773,
            "z": 39.000,
            "t":2.7
        },
        {
            "x": -159.950,
            "y": -104.445,
            "z": 39.000,
            "t":2.8
        },
        {
            "x": -162.467,
            "y": -26.485,
            "z": 39.000,
            "t":6.4
        },
        {
            "x": -167.237,
            "y": -4.562,
            "z": 40.344,
            "t":2.9
        },
        {
            "x": -173.838,
            "y": 11.684,
            "z": 42.001,
            "t":1.9
        },
        {
            "x": -185.836,
            "y": 24.139,
            "z": 41.330,
            "t":1.8
        },
        {
            "x": -201.662,
            "y": 30.477,
            "z": 39.415,
            "t":2.0
        },
        {
            "x": -240.059,
            "y": 37.545,
            "z": 35.123,
            "t":2.9
        }
]
