{
  "level": "ownmap",
  "cars": [
    {
      "car_id": "crasher",
      "position": [-4.24, -184.11, 1.39, 0.00302535, -0.000519328, 0.169184, 0.98558],
      "model": "etk800",
      "ai": "manual",
      "max_speed": 300,
      "cam": true,
      "first_person": false
    },
    {
      "car_id": "target",
      "position": [-32.03, -270.75, 2.90, -0.00209438, 0.000418163, 0.195795, 0.980642],
      "model": "etk800",
      "ai": "manual",
      "max_speed": 40
    }
  ],
  "cameras": [
    {
      "position": [-40.05, -260.07, 2.22, 0.0317373, -0.0234876, 0.594411, 0.803191]
    }
  ]
}